ansi_colours/__init__.py
ansi_colours/ansi_colours.py
ansi_colours-2.0.0.dist-info/WHEEL
ansi_colours-2.0.0.dist-info/METADATA
ansi_colours-2.0.0.dist-info/RECORD
