Metadata-Version: 2.1
Name: ansi-colours
Version: 2.0.0
Summary: Library of static methods for colouring text in terminal output
License: MIT
Author: Sarcoma
Author-email: sarcoma@live.co.uk
Requires-Python: >=3.5,<4.0
Classifier: License :: OSI Approved :: MIT License
Classifier: Programming Language :: Python :: 3
Classifier: Programming Language :: Python :: 3.5
Classifier: Programming Language :: Python :: 3.6
Classifier: Programming Language :: Python :: 3.7
Classifier: Programming Language :: Python :: 3.8
Requires-Dist: codecov (>=2.1.8,<3.0.0)
Requires-Dist: coverage (>=5.2.1,<6.0.0)
Requires-Dist: pytest (>=6.0.1,<7.0.0)
